asciiRyver/__init__.py
asciiRyver/__main__.py
asciiRyver/client.py
asciiRyver/framework.py
asciiRyver-1.3a1.dist-info/DESCRIPTION.rst
asciiRyver-1.3a1.dist-info/METADATA
asciiRyver-1.3a1.dist-info/RECORD
asciiRyver-1.3a1.dist-info/WHEEL
asciiRyver-1.3a1.dist-info/entry_points.txt
asciiRyver-1.3a1.dist-info/metadata.json
asciiRyver-1.3a1.dist-info/top_level.txt
