Metadata-Version: 2.0
Name: asciiRyver
Version: 1.3a1
Summary: Ryver for the terminal
Home-page: https://github.com/lillyjsm/asciiRyver
Author: Jake Lilly
Author-email: Lillyjsm@gmail.com
License: UNKNOWN
Platform: UNKNOWN
Classifier: Development Status :: 2 - Pre-Alpha
Classifier: Intended Audience :: Developers
Classifier: Intended Audience :: End Users/Desktop
Classifier: License :: OSI Approved :: MIT License
Classifier: Programming Language :: Python :: 3 :: Only
Classifier: Programming Language :: Python :: 3.4
Classifier: Programming Language :: Python :: 3.5
Classifier: Programming Language :: Python :: 3.6
Classifier: Topic :: Communications :: Chat
Requires-Dist: requests (==2.18.4)
Requires-Dist: websocket-client (==0.46.0)
Requires-Dist: asciimatics (==1.9.0)
